[
  {
    "subject": {
      "name": "客戶",
      "type": "user"
    },
    "relation": "implements",
    "object": {
      "name": "服務條約",
      "type": "policy"
    },
    "reasoning": "文本提到服務條約是客戶與業者之間協商並同意的約定。在資安本體論中，服務條約（SLA）屬於規範與策略 (policy)，而客戶作為使用方同意並遵守該約定，符合 'user implements policy' 的定義。",
    "source_id": "chunk_7",
    "source_file": "ch11_習題解答.pdf",
    "source_index": 1
  },
  {
    "subject": {
      "name": "系統提供者",
      "type": "securityTeam"
    },
    "relation": "implements",
    "object": {
      "name": "服務條約",
      "type": "policy"
    },
    "reasoning": "系統提供者（業者）是服務的維運方，負責確保服務達到條約中定義的目標與責任。因此，將其歸類為安全團隊/維運角色 (securityTeam)，其執行並遵守服務條約符合 'securityTeam implements policy' 的定義。",
    "source_id": "chunk_7",
    "source_file": "ch11_習題解答.pdf",
    "source_index": 2
  }
]