[
  {
    "subject": {
      "name": "網站",
      "type": "app"
    },
    "relation": "is_part_of",
    "object": {
      "name": "網際網路",
      "type": "system"
    },
    "reasoning": "文本明確提到『網站（web site）是網際網路的應用』，因此將網站視為 app，網際網路視為 system，關係為 is_part_of。",
    "source_id": "chunk_8",
    "source_file": "第16章 電子郵件與網站安全_e5.pdf",
    "source_index": 1
  },
  {
    "subject": {
      "name": "網站",
      "type": "app"
    },
    "relation": "has_a",
    "object": {
      "name": "HTML",
      "type": "feature"
    },
    "reasoning": "文本提到網站使用 HTML 等工具來製作網頁，HTML 在此作為網站建構的技術特徵，符合 ('app', 'has_a', 'feature')。",
    "source_id": "chunk_8",
    "source_file": "第16章 電子郵件與網站安全_e5.pdf",
    "source_index": 2
  },
  {
    "subject": {
      "name": "瀏覽器",
      "type": "app"
    },
    "relation": "connects_to",
    "object": {
      "name": "網站伺服器",
      "type": "system"
    },
    "reasoning": "根據圖 16.14 及文本『瀏覽器向網站送出要求指令』，瀏覽器（app）與網站伺服器（system）之間存在網路連線，符合 ('app', 'connects_to', 'system')。",
    "source_id": "chunk_8",
    "source_file": "第16章 電子郵件與網站安全_e5.pdf",
    "source_index": 3
  },
  {
    "subject": {
      "name": "瀏覽器",
      "type": "app"
    },
    "relation": "uses",
    "object": {
      "name": "HTML",
      "type": "data"
    },
    "reasoning": "文本提到『此語法內容可以為瀏覽器所解析』以及『由瀏覽器解析其內容 HTML』，瀏覽器使用 HTML 資料來呈現畫面，符合 ('app', 'uses', 'data')。",
    "source_id": "chunk_8",
    "source_file": "第16章 電子郵件與網站安全_e5.pdf",
    "source_index": 4
  },
  {
    "subject": {
      "name": "網站伺服器",
      "type": "system"
    },
    "relation": "generates",
    "object": {
      "name": "HTML",
      "type": "data"
    },
    "reasoning": "文本提到『網站回應以網頁 HTML』，表示伺服器系統產生了 HTML 格式的資料回傳給客戶端，符合 ('system', 'generates', 'data')。",
    "source_id": "chunk_8",
    "source_file": "第16章 電子郵件與網站安全_e5.pdf",
    "source_index": 5
  },
  {
    "subject": {
      "name": "使用者",
      "type": "user"
    },
    "relation": "uses",
    "object": {
      "name": "瀏覽器",
      "type": "app"
    },
    "reasoning": "圖 16.14 顯示使用者透過電腦使用瀏覽器來存取網站，符合 ('user', 'uses', 'app')。",
    "source_id": "chunk_8",
    "source_file": "第16章 電子郵件與網站安全_e5.pdf",
    "source_index": 6
  },
  {
    "subject": {
      "name": "使用者",
      "type": "user"
    },
    "relation": "implements",
    "object": {
      "name": "電子郵件安全原則",
      "type": "policy"
    },
    "reasoning": "文本開頭列舉了多項電子郵件使用建議（如：切勿回覆垃圾郵件、不要回覆個人資訊詢問），這些屬於安全操作規範，使用者應執行之，符合 ('user', 'implements', 'policy')。",
    "source_id": "chunk_8",
    "source_file": "第16章 電子郵件與網站安全_e5.pdf",
    "source_index": 7
  },
  {
    "subject": {
      "name": "垃圾郵件",
      "type": "attack"
    },
    "relation": "can_harm",
    "object": {
      "name": "個人資訊",
      "type": "data"
    },
    "reasoning": "文本提到『收到詢問個人資訊的電子郵件時，不要回覆』，暗示垃圾郵件（攻擊手段）旨在獲取或危害個人資訊（資料），符合 ('attack', 'can_harm', 'data')。",
    "source_id": "chunk_8",
    "source_file": "第16章 電子郵件與網站安全_e5.pdf",
    "source_index": 8
  },
  {
    "subject": {
      "name": "語言編輯器",
      "type": "tool"
    },
    "relation": "generates",
    "object": {
      "name": "HTML",
      "type": "data"
    },
    "reasoning": "文本提到『HTML 的撰寫，使用純文字模式的語言編輯器即可』，編輯器工具被用來產生 HTML 檔案資料，符合 ('tool', 'generates', 'data')。",
    "source_id": "chunk_8",
    "source_file": "第16章 電子郵件與網站安全_e5.pdf",
    "source_index": 9
  },
  {
    "subject": {
      "name": "網頁",
      "type": "data"
    },
    "relation": "deployed_in",
    "object": {
      "name": "網站伺服器",
      "type": "system"
    },
    "reasoning": "文本提到網頁存成 .html 檔案並由網站伺服器回應，表示網頁資料部署在伺服器系統中，符合 ('data', 'deployed_in', 'system')。",
    "source_id": "chunk_8",
    "source_file": "第16章 電子郵件與網站安全_e5.pdf",
    "source_index": 10
  }
]