[
  {
    "subject": {
      "name": "電子商務",
      "type": "system",
      "display_name": "電子商務"
    },
    "relation": "depends_on",
    "object": {
      "name": "企業網路",
      "type": "system",
      "display_name": "企業網路"
    },
    "reasoning": "文本提到電子商務應用企業網路（intranet）來進行交易，因此電子商務依賴於企業網路系統。符合 Schema: (\"app\", \"depends_on\", \"system\")",
    "source_id": "chunk_1",
    "source_file": "第02章 電子商務安全_e5.pdf",
    "source_index": 2,
    "validation_history": {
      "step_1": {
        "step_1_list_check": "主體類別 'app'、受體類別 'system' 與關係 'depends_on' 均在 Lc,p 中。",
        "step_2_alignment_check": "電子商務是 'app' 的合理實例，企業網路是 'system' 的合理實例。",
        "response": "correct",
        "reason": "電子商務與企業網路的類別與屬性完全符合預先定義的類別與屬性清單。"
      },
      "step_3": {
        "step_1_rule_matching": "檢查規則1：不適用。檢查規則2：不適用。檢查規則3：不適用。檢查規則4：不適用。檢查規則5：不適用，因為主體類別不是 data。檢查規則6：不適用，因為關係不是 deployed_in。檢查規則7：不適用，因為關係不是 generates。檢查規則8：不適用，因為關係不是 controls。檢查規則，發現沒有直接違反任何規則。",
        "response": "correct",
        "reason": "三元組中的主體和受體類別與關係之間的組合，沒有明確違反語義限制清單中的任何規則。因此，根據無罪推定原則，判定為正確。"
      },
      "step_2": {
        "granularity_analysis": "電子商務與企業網路在資安領域中代表不同的概念，電子商務是一種商業模式，企業網路是指公司內部的網路系統，兩者之間沒有直接的同義詞或從屬關係。",
        "response": "correct",
        "standard_subject": "",
        "standard_object": "",
        "reason": "電子商務和企業網路是不同的系統類別，無同義詞或從屬關係，判定為正確。"
      }
    },
    "original_raw_triple": {
      "subject": {
        "name": "電子商務",
        "type": "app"
      },
      "relation": "depends_on",
      "object": {
        "name": "企業網路",
        "type": "system"
      },
      "reasoning": "文本提到電子商務應用企業網路（intranet）來進行交易，因此電子商務依賴於企業網路系統。符合 Schema: (\"app\", \"depends_on\", \"system\")",
      "source_id": "chunk_1",
      "source_file": "第02章 電子商務安全_e5.pdf",
      "source_index": 2
    }
  },
  {
    "subject": {
      "name": "電子商務",
      "type": "system",
      "display_name": "電子商務"
    },
    "relation": "depends_on",
    "object": {
      "name": "網際網路",
      "type": "system",
      "display_name": "網際網路"
    },
    "reasoning": "文本提到電子商務是應用網際網路來進行交易活動，因此電子商務（應用程式/服務）依賴於網際網路（系統基礎設施）。符合 Schema: (\"app\", \"depends_on\", \"system\")",
    "source_id": "chunk_1",
    "source_file": "第02章 電子商務安全_e5.pdf",
    "source_index": 1,
    "validation_history": {
      "step_1": {
        "step_1_list_check": "電子商務的類別 'app' 存在於 Lc,p 的 'Classes' 中，網際網路的類別 'system' 存在於 Lc,p 的 'Classes' 中，關係 'depends_on' 存在於 Lc,p 的 'Properties' 中。",
        "step_2_alignment_check": "電子商務是 'app' 的合理實例，網際網路是 'system' 的合理實例，且 'depends_on' 關係在資安領域中是合理的。",
        "response": "correct",
        "reason": "電子商務與網際網路的類別和關係完全符合預先定義的類別與屬性清單 Lc,p。"
      },
      "step_3": {
        "step_1_rule_matching": "檢查規則1：不適用。檢查規則2：不適用。檢查規則3：不適用。檢查規則4：不適用。檢查規則5：不適用。檢查規則6：不適用，因為關係為 depends_on，不是 deployed_in。檢查規則7：不適用，因為關係為 depends_on，不是 generates。檢查規則8：不適用，因為關係為 depends_on，不是 controls。",
        "response": "correct",
        "reason": "三元組中的關係 'depends_on' 與規則清單中沒有直接相關的限制，因此不觸發任何違規。"
      },
      "step_2": {
        "granularity_analysis": "電子商務與網際網路是兩個不同的系統概念，前者是指在網際網路上進行的商務活動，後者是指全球性的網路系統。兩者之間沒有直接的同義詞或從屬關係。",
        "response": "correct",
        "standard_subject": "",
        "standard_object": "",
        "reason": "電子商務和網際網路是兩個不同的系統概念，無法判定為同義詞或從屬關係，故保留為正確的實體對齊。"
      }
    },
    "original_raw_triple": {
      "subject": {
        "name": "電子商務",
        "type": "app"
      },
      "relation": "depends_on",
      "object": {
        "name": "網際網路",
        "type": "system"
      },
      "reasoning": "文本提到電子商務是應用網際網路來進行交易活動，因此電子商務（應用程式/服務）依賴於網際網路（系統基礎設施）。符合 Schema: (\"app\", \"depends_on\", \"system\")",
      "source_id": "chunk_1",
      "source_file": "第02章 電子商務安全_e5.pdf",
      "source_index": 1
    }
  },
  {
    "subject": {
      "name": "電子商務",
      "type": "system",
      "display_name": "電子商務"
    },
    "relation": "has_a",
    "object": {
      "name": "電子資金轉換",
      "type": "tool",
      "display_name": "電子資金轉換"
    },
    "reasoning": "電子資金轉換（EFT）是電子商務時代開啟的具體交易工具/機制，視為電子商務應用所包含的工具。符合 Schema: (\"app\", \"has_a\", \"tool\")",
    "source_id": "chunk_1",
    "source_file": "第02章 電子商務安全_e5.pdf",
    "source_index": 4,
    "validation_history": {
      "step_1": {
        "step_1_list_check": "主體類別 'app'、受體類別 'tool' 與關係 'has_a' 均存在於 Lc,p 的 'Classes' 與 'Properties' 中。",
        "step_2_alignment_check": "電子商務 (app) 與電子資金轉換 (tool) 的名稱與其類別合理對齊，電子商務是一種應用程式 (app)，電子資金轉換是一種工具 (tool)。",
        "response": "correct",
        "reason": "電子商務 (app) 與電子資金轉換 (tool) 的三元組完全符合預先定義的類別與屬性清單 Lc,p。"
      },
      "step_3": {
        "step_1_rule_matching": "檢查規則1：不適用。檢查規則2：不適用。檢查規則3：不適用。檢查規則4：不適用。檢查規則5：不適用，因為關係為 'has_a'，不涉及 'uses'。檢查規則6：不適用，因為關係為 'has_a'，不涉及 'deployed_in'。檢查規則7：不適用，因為關係為 'has_a'，不涉及 'generates'。檢查規則8：不適用，因為關係為 'has_a'，不涉及 'controls'。",
        "response": "correct",
        "reason": "三元組中的關係 'has_a' 與主體 '電子商務' 和受體 '電子資金轉換' 的類別組合，沒有明確違反語義限制清單中的任何規則。"
      },
      "step_2": {
        "granularity_analysis": "電子商務與b2b電子商務、c2c電子商務等為廣義/狹義從屬關係，但電子商務與電子資金轉換無直接同義詞或從屬關係。",
        "response": "correct",
        "standard_subject": "",
        "standard_object": "",
        "reason": "無法確定電子商務與電子資金轉換之間的直接關聯，依據不確定時預設保留原則，判定為correct。"
      }
    },
    "original_raw_triple": {
      "subject": {
        "name": "電子商務",
        "type": "app"
      },
      "relation": "has_a",
      "object": {
        "name": "電子資金轉換",
        "type": "tool"
      },
      "reasoning": "電子資金轉換（EFT）是電子商務時代開啟的具體交易工具/機制，視為電子商務應用所包含的工具。符合 Schema: (\"app\", \"has_a\", \"tool\")",
      "source_id": "chunk_1",
      "source_file": "第02章 電子商務安全_e5.pdf",
      "source_index": 4
    }
  },
  {
    "subject": {
      "name": "電子商務",
      "type": "system",
      "display_name": "電子商務"
    },
    "relation": "depends_on",
    "object": {
      "name": "加值網路",
      "type": "system",
      "display_name": "加值網路"
    },
    "reasoning": "文本提到電子商務應用加值網路（value added network）來進行交易，因此電子商務依賴於加值網路系統。符合 Schema: (\"app\", \"depends_on\", \"system\")",
    "source_id": "chunk_1",
    "source_file": "第02章 電子商務安全_e5.pdf",
    "source_index": 3,
    "validation_history": {
      "step_1": {
        "step_1_list_check": "主體類別 'app'、受體類別 'system' 與關係 'depends_on' 都存在於 Lc,p 的 'Classes' 和 'Properties' 中。",
        "step_2_alignment_check": "電子商務是 'app' 的合理實例，且加值網路是 'system' 的合理實例，兩者之間的 'depends_on' 關係在資安領域中是合理的。",
        "response": "correct",
        "reason": "電子商務作為 'app' 類別，依賴加值網路作為 'system' 類別，完全符合預先定義的類別與屬性清單 Lc,p。"
      },
      "step_3": {
        "step_1_rule_matching": "檢查規則1：不適用。檢查規則2：不適用。檢查規則3：不適用。檢查規則4：不適用。檢查規則5：不適用，因為關係為 'depends_on'，不涉及 'uses'。檢查規則6：不適用，因為關係為 'depends_on'，不涉及 'deployed_in'。檢查規則7：不適用，因為關係為 'depends_on'，不涉及 'generates'。檢查規則8：不適用，因為關係為 'depends_on'，不涉及 'controls'。",
        "response": "correct",
        "reason": "三元組中的關係 'depends_on' 與主體 '電子商務' 和受體 '加值網路' 的類別 'system' 不違反任何語義限制清單中的規則。"
      },
      "step_2": {
        "granularity_analysis": "電子商務與Ldr中電子商務完全匹配，受體加值網路與Ldr中企業網路或網際網路有相似之處，但不完全匹配",
        "response": "correct",
        "standard_subject": "",
        "standard_object": "",
        "reason": "根據前提確認，電子商務與Ldr中電子商務完全匹配，且無同義詞重複，故判定為correct。"
      }
    },
    "original_raw_triple": {
      "subject": {
        "name": "電子商務",
        "type": "app"
      },
      "relation": "depends_on",
      "object": {
        "name": "加值網路",
        "type": "system"
      },
      "reasoning": "文本提到電子商務應用加值網路（value added network）來進行交易，因此電子商務依賴於加值網路系統。符合 Schema: (\"app\", \"depends_on\", \"system\")",
      "source_id": "chunk_1",
      "source_file": "第02章 電子商務安全_e5.pdf",
      "source_index": 3
    }
  },
  {
    "subject": {
      "name": "電子商務",
      "type": "system",
      "display_name": "電子商務"
    },
    "relation": "has_a",
    "object": {
      "name": "電子資料交換",
      "type": "tool",
      "display_name": "電子資料交換"
    },
    "reasoning": "電子資料交換（EDI）是電子商務中用於傳輸資料的具體工具/機制。符合 Schema: (\"app\", \"has_a\", \"tool\")",
    "source_id": "chunk_1",
    "source_file": "第02章 電子商務安全_e5.pdf",
    "source_index": 5,
    "validation_history": {
      "step_1": {
        "step_1_list_check": "主體類別 'app'、受體類別 'tool' 與關係 'has_a' 都存在於 Lc,p 的 'Classes' 和 'Properties' 中。",
        "step_2_alignment_check": "電子商務 (app) 和 電子資料交換 (tool) 的名稱與其類別合理對齊，電子商務是一種應用程式 (app)，電子資料交換是一種工具 (tool)。",
        "response": "correct",
        "reason": "電子商務 (app) 與電子資料交換 (tool) 的三元組完全符合預先定義的類別與屬性清單 Lc,p。"
      },
      "step_3": {
        "step_1_rule_matching": "檢查規則1：不適用。檢查規則2：不適用。檢查規則3：不適用。檢查規則4：不適用。檢查規則5：不適用。檢查規則6：不適用。檢查規則7：不適用。檢查規則8：不適用。無直接相關規則觸發違規。",
        "response": "correct",
        "reason": "三元組中的主體和受體之間的關係為 has_a，電子商務系統具有電子資料交換工具，無法直接對應到語義限制清單中的任何規則，因此判定為正確。"
      },
      "step_2": {
        "granularity_analysis": "電子商務與b2b電子商務、c2c電子商務等為廣義/狹義從屬關係，但電子商務與電子資料交換無直接同義詞或從屬關係。",
        "response": "correct",
        "standard_subject": "",
        "standard_object": "",
        "reason": "無法確定電子商務與電子資料交換之間的直接同義詞或從屬關係，故預設保留。"
      }
    },
    "original_raw_triple": {
      "subject": {
        "name": "電子商務",
        "type": "app"
      },
      "relation": "has_a",
      "object": {
        "name": "電子資料交換",
        "type": "tool"
      },
      "reasoning": "電子資料交換（EDI）是電子商務中用於傳輸資料的具體工具/機制。符合 Schema: (\"app\", \"has_a\", \"tool\")",
      "source_id": "chunk_1",
      "source_file": "第02章 電子商務安全_e5.pdf",
      "source_index": 5
    }
  },
  {
    "subject": {
      "name": "電子商務",
      "type": "system",
      "display_name": "電子商務"
    },
    "relation": "has_a",
    "object": {
      "name": "電子郵件",
      "type": "app",
      "display_name": "電子郵件"
    },
    "reasoning": "電子郵件是電子商務應用中使用的通訊工具。符合 Schema: (\"app\", \"has_a\", \"tool\")",
    "source_id": "chunk_1",
    "source_file": "第02章 電子商務安全_e5.pdf",
    "source_index": 6,
    "validation_history": {
      "step_1": {
        "step_1_list_check": "主體類別 'app'、受體類別 'tool' 與關係 'has_a' 均在 Lc,p 中。",
        "step_2_alignment_check": "電子商務可以被視為一個應用程式（app），電子郵件可以被視為一個工具（tool），且 'has_a' 關係在語意上合理，因為電子商務可能包含或使用電子郵件功能。",
        "response": "correct",
        "reason": "電子商務與電子郵件的類別與屬性完全符合預先定義的清單，且語意對齊合理。"
      },
      "step_3": {
        "step_1_rule_matching": "檢查規則1：不適用。檢查規則2：不適用。檢查規則3：不適用。檢查規則4：不適用。檢查規則5：不適用，因為主體的類別不是 data。檢查規則6：不適用，因為關係不是 deployed_in。檢查規則7：不適用，因為關係不是 generates。檢查規則8：不適用，因為關係不是 controls。檢查規則沒有直接觸發違規。",
        "response": "correct",
        "reason": "三元組中的主體和受體之間的關係 'has_a' 沒有明確違反語義限制清單中的任何規則。"
      },
      "step_2": {
        "granularity_analysis": "電子商務與電子郵件之間沒有直接的同義詞或從屬關係，兩者屬於不同類別的資源",
        "response": "correct",
        "standard_subject": "",
        "standard_object": "",
        "reason": "根據判斷準則，電子商務和電子郵件沒有同義詞關係，也不是廣義或狹義的從屬關係，因此判定為 correct。"
      }
    },
    "original_raw_triple": {
      "subject": {
        "name": "電子商務",
        "type": "app"
      },
      "relation": "has_a",
      "object": {
        "name": "電子郵件",
        "type": "tool"
      },
      "reasoning": "電子郵件是電子商務應用中使用的通訊工具。符合 Schema: (\"app\", \"has_a\", \"tool\")",
      "source_id": "chunk_1",
      "source_file": "第02章 電子商務安全_e5.pdf",
      "source_index": 6
    }
  },
  {
    "subject": {
      "name": "安全威脅",
      "type": "risk",
      "display_name": "安全威脅"
    },
    "relation": "can_harm",
    "object": {
      "name": "電子商務",
      "type": "system",
      "display_name": "電子商務"
    },
    "reasoning": "文本明確指出「網路一旦受到安全威脅，電子商務也將遭受到嚴重的損失」，因此安全威脅（攻擊）可危害電子商務（應用）。符合 Schema: (\"attack\", \"can_harm\", \"app\")",
    "source_id": "chunk_1",
    "source_file": "第02章 電子商務安全_e5.pdf",
    "source_index": 7,
    "validation_history": {
      "step_1": {
        "step_1_list_check": "主體類別 'attack'、受體類別 'app' 與關係 'can_harm' 都存在於 Lc,p 的 'Classes' 和 'Properties' 中。",
        "step_2_alignment_check": "安全威脅 (attack) 是攻擊類別的合理實例，電子商務 (app) 是應用程式類別的合理實例，'can_harm' 關係在資安領域中是合理的，因為攻擊可以對應用程式造成傷害。",
        "response": "correct",
        "reason": "三元組完全符合預先定義的類別與屬性清單，且語意對齊合理。"
      },
      "step_3": {
        "step_1_rule_matching": "檢查規則1：不適用。檢查規則2：不適用。檢查規則3：不適用。檢查規則4：不適用。檢查規則5：不適用。檢查規則6：不適用。檢查規則7：不適用。檢查規則8：不適用。由於三元組中的關係是 'can_harm'，而這個關係在給定的規則中沒有明確的限制，因此不觸發任何違規。",
        "response": "correct",
        "reason": "三元組中的關係 'can_harm' 沒有在給定的語義限制清單中被明確限制，且主體和受體的類別與關係之間沒有直接違反任何規則。"
      },
      "step_2": {
        "granularity_analysis": "電子商務是系統的一種，與網際網路、企業網路、加值網路等同屬系統類別，但安全威脅與電子商務之間的關係是風險對象的關係，而非同義詞或廣義/狹義從屬關係。",
        "response": "correct",
        "standard_subject": "",
        "standard_object": "",
        "reason": "安全威脅與電子商務之間的關係是風險對象的關係，非同義詞或廣義/狹義從屬關係，故判定為 correct。"
      }
    },
    "original_raw_triple": {
      "subject": {
        "name": "安全威脅",
        "type": "attack"
      },
      "relation": "can_harm",
      "object": {
        "name": "電子商務",
        "type": "app"
      },
      "reasoning": "文本明確指出「網路一旦受到安全威脅，電子商務也將遭受到嚴重的損失」，因此安全威脅（攻擊）可危害電子商務（應用）。符合 Schema: (\"attack\", \"can_harm\", \"app\")",
      "source_id": "chunk_1",
      "source_file": "第02章 電子商務安全_e5.pdf",
      "source_index": 7
    }
  }
]