[
  {
    "subject": {
      "name": "行動電話",
      "type": "system"
    },
    "relation": "has_a",
    "object": {
      "name": "SIM卡",
      "type": "tool"
    },
    "reasoning": "文本提到數位式行動電話中包含SIM卡，且缺少該卡則無法使用。根據 Schema，system 可以 has_a tool。",
    "source_id": "chunk_2",
    "source_file": "ch15_習題解答.pdf",
    "source_index": 1
  },
  {
    "subject": {
      "name": "SIM卡",
      "type": "system"
    },
    "relation": "uses",
    "object": {
      "name": "安全資料",
      "type": "data"
    },
    "reasoning": "文本指出 SIM 卡內儲存保護使用者的安全資料。將 SIM 卡視為一個小型嵌入式系統 (system)，根據 Schema，system 可以 uses data。",
    "source_id": "chunk_2",
    "source_file": "ch15_習題解答.pdf",
    "source_index": 2
  },
  {
    "subject": {
      "name": "SIM卡",
      "type": "tool"
    },
    "relation": "has_a",
    "object": {
      "name": "驗證",
      "type": "function"
    },
    "reasoning": "文本提到用戶需通過 SIM 卡的驗證才能使用電話。驗證是一種功能 (function)，根據 Schema，tool 可以 has_a function。",
    "source_id": "chunk_2",
    "source_file": "ch15_習題解答.pdf",
    "source_index": 3
  },
  {
    "subject": {
      "name": "健保IC卡",
      "type": "system"
    },
    "relation": "uses",
    "object": {
      "name": "個人基本資料",
      "type": "data"
    },
    "reasoning": "文本提到健保IC卡的晶片內記錄了個人基本資料段。將 IC 卡視為系統 (system)，根據 Schema，system 可以 uses data。",
    "source_id": "chunk_2",
    "source_file": "ch15_習題解答.pdf",
    "source_index": 4
  },
  {
    "subject": {
      "name": "八達通",
      "type": "tool"
    },
    "relation": "is_part_of",
    "object": {
      "name": "智慧卡電子系統",
      "type": "system"
    },
    "reasoning": "文本提到八達通是該套電子收費系統中採用的 IC 卡。根據 Schema，tool 可以 is_part_of system。",
    "source_id": "chunk_2",
    "source_file": "ch15_習題解答.pdf",
    "source_index": 5
  },
  {
    "subject": {
      "name": "IC金融卡",
      "type": "system"
    },
    "relation": "uses",
    "object": {
      "name": "寢室門禁資料",
      "type": "data"
    },
    "reasoning": "文本提到 IC 金融卡內部可儲存寢室門禁資料。將其視為系統 (system)，根據 Schema，system 可以 uses data。",
    "source_id": "chunk_2",
    "source_file": "ch15_習題解答.pdf",
    "source_index": 6
  },
  {
    "subject": {
      "name": "IC金融卡",
      "type": "system"
    },
    "relation": "uses",
    "object": {
      "name": "圖書館借書資料",
      "type": "data"
    },
    "reasoning": "文本提到 IC 金融卡內部可儲存圖書館借書資料。將其視為系統 (system)，根據 Schema，system 可以 uses data。",
    "source_id": "chunk_2",
    "source_file": "ch15_習題解答.pdf",
    "source_index": 7
  }
]